sparcdownsample
